emoji2text/__init__.py
emoji2text/emoji-test.txt
emoji2text/parse.py
emoji2text-0.1.7.dist-info/DESCRIPTION.rst
emoji2text-0.1.7.dist-info/METADATA
emoji2text-0.1.7.dist-info/RECORD
emoji2text-0.1.7.dist-info/WHEEL
emoji2text-0.1.7.dist-info/metadata.json
emoji2text-0.1.7.dist-info/top_level.txt
